[
  {
    "id": "0b7dc03f-eada-4167-a11e-17528eb31c4c",
    "username": "john123",
    "email": "john123@gmail.com",
    "createdAt": "October 15, 2023 05:35:32",
    "bio": "hi this is a bio",
    "isFollowing": false,
    "followers": "3",
    "following": "5",
    "location": "Vancouver Canada",
    "name": "john",
    "coverImage": "https://images.unsplash.com/photo-1586672806791-3a67d24186c0?q=80&w=1000&auto=format&fit=crop&ixlib=rb-4.0.3&ixid=M3wxMjA3fDB8MHxzZWFyY2h8Mnx8Y292ZXIlMjBhcnR8ZW58MHx8MHx8fDA%3D",
    "profileImage": "https://res.cloudinary.com/demo/image/twitter/1330457336.jpg",
    "password": "$2a$14$dxOGXe76AVBkasKUf5S4WuuQtBpei8FNU/JeC/JN1XsbpuKWnhr.6",
    "posts": [
      {
        "id": "24684da3-9abb-4bac-a0cc-b51bed8768b0",
        "createdAt": "October 15, 2023 05:35:32",
        "title": "go to mall",
        "body": "relax",
        "comments": [],
        "hasLiked": false,
        "likes": 0,
        "user": {
          "id": "0b7dc03f-eada-4167-a11e-17528eb31c4c",
          "name": "john",
          "username": "john123",
          "email": "john123@gmail.com",
          "profileImage": "https://res.cloudinary.com/demo/image/twitter/1330457336.jpg"
        }
      },
      {
        "id": "26684da3-9abb-4bac-a0cc-b51bed8768b0",
        "createdAt": "October 15, 2023 05:35:32",
        "title": "cool app",
        "body": "cool app",
        "comments": 0,
        "hasLiked": false,
        "likes": 0,
        "user": {
          "id": "0b7dc03f-eada-4167-a11e-17528eb31c4c",
          "name": "john",
          "username": "john123",
          "hasNewNotifications": true,
          "email": "john123@gmail.com",
          "profileImage": "https://res.cloudinary.com/demo/image/twitter/1330457336.jpg"
        }
      },
      {
        "id": "8949b449-9c58-4140-855d-cf5fef171f51",
        "createdAt": "October 15, 2023 05:35:32",
        "title": "nice app",
        "body": "nice app",
        "comments": 0,
        "hasLiked": false,
        "likes": 0,
        "user": {
          "id": "0b7dc03f-eada-4167-a11e-17528eb31c4c",
          "name": "john",
          "username": "john123",
          "hasNewNotifications": true,
          "email": "john123@gmail.com",
          "profileImage": "https://res.cloudinary.com/demo/image/twitter/1330457336.jpg"
        }
      },
      {
        "id": "b6ba3261-f35e-4ced-acdf-419480975321",
        "createdAt": "October 15, 2023 05:35:32",
        "title": "fantastic functionality, great job.",
        "body": "fantastic functionality, great job.",
        "comments": 0,
        "hasLiked": false,
        "likes": 0,
        "user": {
          "id": "0b7dc03f-eada-4167-a11e-17528eb31c4c",
          "name": "john",
          "username": "john123",
          "hasNewNotifications": true,
          "email": "john123@gmail.com",
          "profileImage": "https://res.cloudinary.com/demo/image/twitter/1330457336.jpg"
        }
      },
      {
        "id": "a6d83011-152a-4f52-8df8-4c8e23c5d41b",
        "createdAt": "October 15, 2023 05:35:32",
        "title": "great app",
        "body": "great app",
        "followers": [],
        "following": [],
        "isFollowing": false,
        "comments": 0,
        "hasLiked": false,
        "likes": 0,
        "user": {
          "id": "0b7dc03f-eada-4167-a11e-17528eb31c4c",
          "name": "john",
          "username": "john123",
          "createdAt": "October 15, 2023 05:35:32",
          "hasNewNotifications": true,
          "isFollowing": false,
          "following": 0,
          "comments": 0,
          "followers": [],
          "email": "john123@gmail.com",
          "profileImage": "https://res.cloudinary.com/demo/image/twitter/1330457336.jpg"
        }
      }
    ]
  },
  {
    "id": "aa8dc2ed-7fe9-465f-9c04-ed2fe27bc321",
    "username": "sandra123",
    "email": "sandra123@gmail.com",
    "createdAt": "October 15, 2023 05:35:32",
    "bio": "hi this is a bio",
    "isFollowing": false,
    "followers": "3",
    "following": "5",
    "location": "Vancouver Canada",
    "name": "sandra",
    "coverImage": "https://images.unsplash.com/photo-1586672806791-3a67d24186c0?q=80&w=1000&auto=format&fit=crop&ixlib=rb-4.0.3&ixid=M3wxMjA3fDB8MHxzZWFyY2h8Mnx8Y292ZXIlMjBhcnR8ZW58MHx8MHx8fDA%3D",
    "profileImage": "https://cla.umn.edu/sites/cla.umn.edu/files/styles/profile_photo/public/pictures/2022-07/MeredithLiza-2022-500x500.jpg?h=2a479378&itok=FsUH1kIc",
    "password": "$2a$14$Gn34vEwGfSPKMb7BvIBeD.TRlw8X4LyMUwerO.uqiT8lQl9ERkw.y",
    "posts": [
      {
        "id": "1",
        "createdAt": "October 15, 2023 05:35:32",
        "hasLiked": false,
        "title": "go to hawaii",
        "likes": 0,
        "body": "relax",
        "comments": 0,
        "user": {
          "id": "aa8dc2ed-7fe9-465f-9c04-ed2fe27bc321",
          "name": "sandra",
          "username": "sandra123",
          "email": "sandra123@gmail.com",
          "profileImage": "https://cla.umn.edu/sites/cla.umn.edu/files/styles/profile_photo/public/pictures/2022-07/MeredithLiza-2022-500x500.jpg?h=2a479378&itok=FsUH1kIc"
        }
      }
    ]
  }
]